<?xml version="1.0"?>
<!DOCTYPE hibernate-mapping PUBLIC "-//Hibernate/Hibernate Mapping DTD 3.0//EN"
"http://www.hibernate.org/dtd/hibernate-mapping-3.0.dtd">
<!-- Generated 1/10/2015 08:51:29 AM by Hibernate Tools 4.3.1 -->
<hibernate-mapping>
    <class name="com.mx.teknei.pc.lib.entities.CctmArpo" table="cctm_arpo" schema="sitm" optimistic-lock="version">
        <comment>Tabla de Prioridades del Monitor de Alarmas</comment>
        <id name="idArpo" type="int">
            <column name="id_arpo" />
            <generator class="assigned" />
        </id>
        <property name="nameArpo" type="string">
            <column name="name_arpo" length="20" not-null="true">
                <comment>Nombre de Prioridad</comment>
            </column>
        </property>
        <property name="valeArpo" type="int">
            <column name="vale_arpo" not-null="true">
                <comment>Valor</comment>
            </column>
        </property>
        <property name="colrArpo" type="int">
            <column name="colr_arpo" not-null="true">
                <comment>Color</comment>
            </column>
        </property>
        <property name="idEsta" type="int">
            <column name="id_esta" not-null="true">
                <comment>Estatus del Dato</comment>
            </column>
        </property>
        <property name="idTipo" type="int">
            <column name="id_tipo" not-null="true">
                <comment>Tipo del Dato</comment>
            </column>
        </property>
        <property name="usrCrea" type="string">
            <column name="usr_crea" length="10" not-null="true">
                <comment>usuario que crea registro</comment>
            </column>
        </property>
        <property name="fchCrea" type="timestamp">
            <column name="fch_crea" length="29" not-null="true">
                <comment>fecha creacion de registro</comment>
            </column>
        </property>
        <property name="usrModi" type="string">
            <column name="usr_modi" length="10">
                <comment>usuario que modifica registro</comment>
            </column>
        </property>
        <property name="fchModi" type="timestamp">
            <column name="fch_modi" length="29">
                <comment>fecha modificacion de registro</comment>
            </column>
        </property>
        <property name="idConSis" type="java.lang.Integer">
            <column name="id_con_sis" />
        </property>
        <set name="sfalConfs" table="sfal_conf" inverse="true" lazy="true" fetch="select">
            <key>
                <column name="id_arpo">
                    <comment>Nivel de prioridad de alarma</comment>
                </column>
            </key>
            <one-to-many class="com.mx.teknei.pc.lib.entities.SfalConf" />
        </set>
    </class>
</hibernate-mapping>
